samplepoetpackage/__init__.py
samplepoetpackage/example.py
samplepoetpackage-0.1.3.dist-info/WHEEL
samplepoetpackage-0.1.3.dist-info/METADATA
samplepoetpackage-0.1.3.dist-info/RECORD
