Metadata-Version: 2.1
Name: samplepoetpackage
Version: 0.1.3
Summary: Testing poetry out by building a py package!
Home-page: https://github.com/rosikand/samplepoetpackage
License: MIT
Keywords: packaging,poetry
Author: Rohan Sikand
Author-email: rsikand29@gmail.com
Requires-Python: >=3.8,<4.0
Classifier: License :: OSI Approved :: MIT License
Classifier: Programming Language :: Python :: 3
Classifier: Programming Language :: Python :: 3.8
Classifier: Programming Language :: Python :: 3.9
Classifier: Programming Language :: Python :: 3.10
Classifier: Programming Language :: Python :: 3.11
Requires-Dist: numpy (==1.23.3)
